djangoproject_wizard
