Metadata-Version: 1.0
Name: djangoproject-wizard
Version: 1.1a
Summary: Create a Django project layout based on Lincoln Loop best practices.
Home-page: UNKNOWN
Author: Modified by Gilson Filho (Source: Lincoln Loop)
Author-email: contato@gilsondev.com
License: UNKNOWN
Platform: UNKNOWN
Classifier: Development Status :: 3 - Alpha
Classifier: Environment :: Web Environment
Classifier: Intended Audience :: Developers
Classifier: License :: OSI Approved :: MIT License
Classifier: Operating System :: OS Independent
Classifier: Programming Language :: Python
Classifier: Framework :: Django
